crawlmap/__init__.py
crawlmap/__main__.py
crawlmap/functions/__init__.py
crawlmap/functions/burp.py
crawlmap/functions/gospider.py
crawlmap/functions/misc.py
crawlmap/functions/zaproxy.py
crawlmap-1.3.dist-info/LICENSE
crawlmap-1.3.dist-info/METADATA
crawlmap-1.3.dist-info/WHEEL
crawlmap-1.3.dist-info/entry_points.txt
crawlmap-1.3.dist-info/top_level.txt
crawlmap-1.3.dist-info/RECORD
