Metadata-Version: 2.1
Name: crawlmap
Version: 1.3
Summary: A python3 script to change your crawling logs to a mindmap
Home-page: https://github.com/Liodeus/Crawlmap
Author: Liodeus
License: GPL-3.0 License
Keywords: python,pentesting,bugbounty,security,mindmap,crawl,crawling
Platform: UNKNOWN
Classifier: Programming Language :: Python :: 3
Classifier: Topic :: Security
Classifier: Intended Audience :: Developers
Classifier: Intended Audience :: Information Technology
License-File: LICENSE
Requires-Dist: haralyzer
